lexode.py
lexode-0.3.0.dist-info/LICENSE
lexode-0.3.0.dist-info/WHEEL
lexode-0.3.0.dist-info/METADATA
lexode-0.3.0.dist-info/RECORD
