Metadata-Version: 2.1
Name: lexode
Version: 0.3.0
Summary: Lexicographic packing and unpacking
License: Apache
Author: Amirouche
Author-email: amirouche@hyper.dev
Requires-Python: >=3.7,<4.0
Classifier: License :: Other/Proprietary License
Classifier: Programming Language :: Python :: 3
Classifier: Programming Language :: Python :: 3.10
Classifier: Programming Language :: Python :: 3.7
Classifier: Programming Language :: Python :: 3.8
Classifier: Programming Language :: Python :: 3.9
